<annotation verified="no">
  <folder>IP103_final_new4</folder>
  <filename>IP024002672</filename>
  <path>/home/ubuntu3/Desktop/IP103_final_new4/IP024002672.jpg</path>
  <source>
    <database>Unknown</database>
  </source>
  <size>
    <width>1000</width>
    <height>523</height>
    <depth>3</depth>
  </size>
  <segmented>0</segmented>
  <object>
    <name>24</name>
    <pose>Unspecified</pose>
    <truncated>0</truncated>
    <difficult>0</difficult>
    <bndbox>
      <xmin>256</xmin>
      <ymin>192</ymin>
      <xmax>522</xmax>
      <ymax>373</ymax>
    </bndbox>
  </object>
  <object>
    <name>24</name>
    <pose>Unspecified</pose>
    <truncated>0</truncated>
    <difficult>0</difficult>
    <bndbox>
      <xmin>123</xmin>
      <ymin>199</ymin>
      <xmax>288</xmax>
      <ymax>292</ymax>
    </bndbox>
  </object>
  <object>
    <name>24</name>
    <pose>Unspecified</pose>
    <truncated>0</truncated>
    <difficult>0</difficult>
    <bndbox>
      <xmin>191</xmin>
      <ymin>60</ymin>
      <xmax>369</xmax>
      <ymax>165</ymax>
    </bndbox>
  </object>
  <object>
    <name>24</name>
    <pose>Unspecified</pose>
    <truncated>0</truncated>
    <difficult>0</difficult>
    <bndbox>
      <xmin>480</xmin>
      <ymin>194</ymin>
      <xmax>697</xmax>
      <ymax>311</ymax>
    </bndbox>
  </object>
  <object>
    <name>24</name>
    <pose>Unspecified</pose>
    <truncated>0</truncated>
    <difficult>0</difficult>
    <bndbox>
      <xmin>99</xmin>
      <ymin>327</ymin>
      <xmax>253</xmax>
      <ymax>431</ymax>
    </bndbox>
  </object>
  <object>
    <name>24</name>
    <pose>Unspecified</pose>
    <truncated>0</truncated>
    <difficult>0</difficult>
    <bndbox>
      <xmin>691</xmin>
      <ymin>280</ymin>
      <xmax>854</xmax>
      <ymax>425</ymax>
    </bndbox>
  </object>
  <object>
    <name>24</name>
    <pose>Unspecified</pose>
    <truncated>0</truncated>
    <difficult>0</difficult>
    <bndbox>
      <xmin>399</xmin>
      <ymin>39</ymin>
      <xmax>552</xmax>
      <ymax>175</ymax>
    </bndbox>
  </object>
</annotation>
