<annotation verified="yes">
  <folder>IP103_final_new2</folder>
  <filename>IP048000743</filename>
  <path>C:\Users\24740\Desktop\IP103_final_new2\IP048000743.jpg</path>
  <source>
    <database>Unknown</database>
  </source>
  <size>
    <width>720</width>
    <height>467</height>
    <depth>3</depth>
  </size>
  <segmented>0</segmented>
  <object>
    <name>47</name>
    <pose>Unspecified</pose>
    <truncated>0</truncated>
    <difficult>0</difficult>
    <bndbox>
      <xmin>354</xmin>
      <ymin>128</ymin>
      <xmax>633</xmax>
      <ymax>312</ymax>
    </bndbox>
  </object>
</annotation>
