<annotation verified="yes">
  <folder>Untitled Folder</folder>
  <filename>IP052000352</filename>
  <path>F:\Untitled Folder\IP052000352.jpg</path>
  <source>
    <database>Unknown</database>
  </source>
  <size>
    <width>500</width>
    <height>328</height>
    <depth>3</depth>
  </size>
  <segmented>0</segmented>
  <object>
    <name>51</name>
    <pose>Unspecified</pose>
    <truncated>0</truncated>
    <difficult>0</difficult>
    <bndbox>
      <xmin>24</xmin>
      <ymin>63</ymin>
      <xmax>409</xmax>
      <ymax>287</ymax>
    </bndbox>
  </object>
</annotation>
