<annotation verified="no">
  <folder>IP103_final_new3</folder>
  <filename>IP059000690</filename>
  <path>C:\Users\Kunimitsu Tezuka\Desktop\IP103_final_new3\IP059000690.jpg</path>
  <source>
    <database>Unknown</database>
  </source>
  <size>
    <width>220</width>
    <height>187</height>
    <depth>3</depth>
  </size>
  <segmented>0</segmented>
  <object>
    <name>58</name>
    <pose>Unspecified</pose>
    <truncated>0</truncated>
    <difficult>0</difficult>
    <bndbox>
      <xmin>32</xmin>
      <ymin>23</ymin>
      <xmax>111</xmax>
      <ymax>167</ymax>
    </bndbox>
  </object>
  <object>
    <name>58</name>
    <pose>Unspecified</pose>
    <truncated>0</truncated>
    <difficult>0</difficult>
    <bndbox>
      <xmin>122</xmin>
      <ymin>87</ymin>
      <xmax>160</xmax>
      <ymax>125</ymax>
    </bndbox>
  </object>
  <object>
    <name>58</name>
    <pose>Unspecified</pose>
    <truncated>0</truncated>
    <difficult>0</difficult>
    <bndbox>
      <xmin>132</xmin>
      <ymin>126</ymin>
      <xmax>168</xmax>
      <ymax>171</ymax>
    </bndbox>
  </object>
</annotation>
