<annotation verified="no">
  <folder>IP103_final_new3</folder>
  <filename>IP052001383</filename>
  <path>C:\Users\Kunimitsu Tezuka\Desktop\IP103_final_new3\IP052001383.jpg</path>
  <source>
    <database>Unknown</database>
  </source>
  <size>
    <width>500</width>
    <height>303</height>
    <depth>3</depth>
  </size>
  <segmented>0</segmented>
  <object>
    <name>51</name>
    <pose>Unspecified</pose>
    <truncated>0</truncated>
    <difficult>0</difficult>
    <bndbox>
      <xmin>167</xmin>
      <ymin>44</ymin>
      <xmax>457</xmax>
      <ymax>239</ymax>
    </bndbox>
  </object>
</annotation>
