<annotation verified="yes">
  <folder>Untitled Folder</folder>
  <filename>IP052000106</filename>
  <path>F:\Untitled Folder\IP052000106.jpg</path>
  <source>
    <database>Unknown</database>
  </source>
  <size>
    <width>565</width>
    <height>521</height>
    <depth>3</depth>
  </size>
  <segmented>0</segmented>
  <object>
    <name>51</name>
    <pose>Unspecified</pose>
    <truncated>0</truncated>
    <difficult>0</difficult>
    <bndbox>
      <xmin>85</xmin>
      <ymin>73</ymin>
      <xmax>498</xmax>
      <ymax>471</ymax>
    </bndbox>
  </object>
</annotation>
