<annotation verified="no">
  <folder>IP103_final_new3</folder>
  <filename>IP063000071</filename>
  <path>C:\Users\Kunimitsu Tezuka\Desktop\IP103_final_new3\IP063000071.jpg</path>
  <source>
    <database>Unknown</database>
  </source>
  <size>
    <width>500</width>
    <height>361</height>
    <depth>3</depth>
  </size>
  <segmented>0</segmented>
  <object>
    <name>62</name>
    <pose>Unspecified</pose>
    <truncated>0</truncated>
    <difficult>0</difficult>
    <bndbox>
      <xmin>105</xmin>
      <ymin>80</ymin>
      <xmax>302</xmax>
      <ymax>297</ymax>
    </bndbox>
  </object>
  <object>
    <name>62</name>
    <pose>Unspecified</pose>
    <truncated>0</truncated>
    <difficult>0</difficult>
    <bndbox>
      <xmin>244</xmin>
      <ymin>79</ymin>
      <xmax>421</xmax>
      <ymax>248</ymax>
    </bndbox>
  </object>
</annotation>
