<annotation verified="no">
  <folder>&#26032;&#24314;&#25991;&#20214;&#22841;</folder>
  <filename>IP069000718</filename>
  <path>C:\Users\11202\Desktop\&#26032;&#24314;&#25991;&#20214;&#22841;\IP069000718.jpg</path>
  <source>
    <database>Unknown</database>
  </source>
  <size>
    <width>193</width>
    <height>360</height>
    <depth>3</depth>
  </size>
  <segmented>0</segmented>
  <object>
    <name>68</name>
    <pose>Unspecified</pose>
    <truncated>0</truncated>
    <difficult>0</difficult>
    <bndbox>
      <xmin>18</xmin>
      <ymin>39</ymin>
      <xmax>167</xmax>
      <ymax>338</ymax>
    </bndbox>
  </object>
</annotation>
