<annotation verified="no">
  <folder>IP103_final_new3</folder>
  <filename>IP077000545</filename>
  <path>C:\Users\dell\Desktop\IP103_final_new3\IP077000545.jpg</path>
  <source>
    <database>Unknown</database>
  </source>
  <size>
    <width>305</width>
    <height>214</height>
    <depth>3</depth>
  </size>
  <segmented>0</segmented>
  <object>
    <name>76</name>
    <pose>Unspecified</pose>
    <truncated>0</truncated>
    <difficult>0</difficult>
    <bndbox>
      <xmin>34</xmin>
      <ymin>3</ymin>
      <xmax>300</xmax>
      <ymax>194</ymax>
    </bndbox>
  </object>
</annotation>
