<annotation verified="no">
  <folder>IP103_final_new3</folder>
  <filename>IP087000509</filename>
  <path>C:\Users\dell\Desktop\IP103_final_new3\IP087000509.jpg</path>
  <source>
    <database>Unknown</database>
  </source>
  <size>
    <width>2560</width>
    <height>1920</height>
    <depth>3</depth>
  </size>
  <segmented>0</segmented>
  <object>
    <name>86</name>
    <pose>Unspecified</pose>
    <truncated>0</truncated>
    <difficult>0</difficult>
    <bndbox>
      <xmin>893</xmin>
      <ymin>337</ymin>
      <xmax>1869</xmax>
      <ymax>1470</ymax>
    </bndbox>
  </object>
</annotation>
