<annotation verified="no">
  <folder>IP103_final_new4</folder>
  <filename>IP102001636</filename>
  <path>/home/ubuntu3/Desktop/IP103_final_new4/IP102001636.jpg</path>
  <source>
    <database>Unknown</database>
  </source>
  <size>
    <width>800</width>
    <height>534</height>
    <depth>3</depth>
  </size>
  <segmented>0</segmented>
  <object>
    <name>101</name>
    <pose>Unspecified</pose>
    <truncated>0</truncated>
    <difficult>0</difficult>
    <bndbox>
      <xmin>86</xmin>
      <ymin>173</ymin>
      <xmax>586</xmax>
      <ymax>449</ymax>
    </bndbox>
  </object>
</annotation>
