<annotation verified="no">
  <folder>IP103_final_new4</folder>
  <filename>IP101000286</filename>
  <path>/home/ubuntu3/Desktop/IP103_final_new4/IP101000286.jpg</path>
  <source>
    <database>Unknown</database>
  </source>
  <size>
    <width>499</width>
    <height>427</height>
    <depth>3</depth>
  </size>
  <segmented>0</segmented>
  <object>
    <name>100</name>
    <pose>Unspecified</pose>
    <truncated>0</truncated>
    <difficult>0</difficult>
    <bndbox>
      <xmin>39</xmin>
      <ymin>11</ymin>
      <xmax>480</xmax>
      <ymax>420</ymax>
    </bndbox>
  </object>
</annotation>
